easy_audio_interfaces/__init__.py
easy_audio_interfaces/audio_interfaces.py
easy_audio_interfaces/base_interfaces.py
easy_audio_interfaces/streaming.py
easy_audio_interfaces/utils.py
easy_audio_interfaces/extras/__init__.py
easy_audio_interfaces/extras/_models.py
easy_audio_interfaces/extras/friend_bluetooth.py
easy_audio_interfaces/extras/local_audio.py
easy_audio_interfaces/filesystem/__init__.py
easy_audio_interfaces/filesystem/filesystem_interfaces.py
easy_audio_interfaces/network/__init__.py
easy_audio_interfaces/network/network_interfaces.py
easy_audio_interfaces/tests/__init__.py
easy_audio_interfaces/tests/test_filesystem_interfaces.py
easy_audio_interfaces/tests/test_network_interfaces.py
easy_audio_interfaces/tests/test_processing_interfaces.py
easy_audio_interfaces/tests/test_tcp_interfaces.py
easy_audio_interfaces/tests/utils.py
easy_audio_interfaces/types/__init__.py
easy_audio_interfaces/types/common.py
easy_audio_interfaces-0.7.1.dist-info/licenses/LICENSE
easy_audio_interfaces-0.7.1.dist-info/METADATA
easy_audio_interfaces-0.7.1.dist-info/WHEEL
easy_audio_interfaces-0.7.1.dist-info/top_level.txt
easy_audio_interfaces-0.7.1.dist-info/zip-safe
easy_audio_interfaces-0.7.1.dist-info/RECORD
