Metadata-Version: 2.4
Name: easy-audio-interfaces
Version: 0.7.1
Summary: Easy Audio Interfaces is a Python library that provides a simple and flexible way to work with audio streams, including recording, playback, network transfer, and processing.
Author-email: Ankush Malaker <43288948+AnkushMalaker@users.noreply.github.com>
Platform: any
Requires-Python: <3.13,>=3.9
License-File: LICENSE
Requires-Dist: fire<0.6.0,>=0.5.0
Requires-Dist: rich<14.0.0,>=13.5.3
Requires-Dist: opuslib<4.0.0,>=3.0.1
Requires-Dist: websockets>=14.0
Requires-Dist: scipy>=1.13.1
Requires-Dist: wyoming>=1.6.1
Requires-Dist: soxr>=0.5.0.post1
Provides-Extra: stt
Requires-Dist: faster-whisper; extra == "stt"
Provides-Extra: silero-vad
Requires-Dist: torch; extra == "silero-vad"
Requires-Dist: torchaudio; extra == "silero-vad"
Provides-Extra: bluetooth
Requires-Dist: bleak; extra == "bluetooth"
Provides-Extra: local-audio
Requires-Dist: pyaudio; extra == "local-audio"
Provides-Extra: test
Requires-Dist: pytest; extra == "test"
Requires-Dist: pytest-asyncio; extra == "test"
Requires-Dist: hypothesis>=6.135.12; extra == "test"
Dynamic: license-file
